cryo_python-0.3.0.dist-info/METADATA
cryo_python-0.3.0.dist-info/WHEEL
cryo/_collect.py
cryo/_freeze.py
cryo/_args.py
cryo/__init__.py
cryo/_spec.py
cryo/_cryo_rust.cpython-39-darwin.so
cryo_python-0.3.0.dist-info/RECORD
