Metadata-Version: 2.1
Name: cryo_python
Version: 0.3.0
Classifier: Programming Language :: Rust
Classifier: Programming Language :: Python :: Implementation :: CPython
Classifier: Programming Language :: Python :: Implementation :: PyPy
Summary: cryo is the easiest way to extract blockchain data to parquet, csv, json, or a python dataframe.
Home-Page: https://github.com/paradigmxyz/cryo
License: MIT OR Apache-2.0
Requires-Python: >=3.7
Project-URL: Source Code, https://github.com/paradigmxyz/cryo
